spotON_sdk/__init__.py
spotON_sdk/spotON_controller.py
spotON_sdk/API/API_Call.py
spotON_sdk/API/__init__.py
spotON_sdk/API/HASS/auth.py
spotON_sdk/API/HASS/hub.py
spotON_sdk/API/HASS/light.py
spotON_sdk/Logic/__init__.py
spotON_sdk/Logic/Feedback/Feedback.py
spotON_sdk/Logic/Feedback/Sensors.py
spotON_sdk/Logic/Feedback/Units.py
spotON_sdk/Logic/Feedback/__init__.py
spotON_sdk/Logic/Output/Switchtypes.py
spotON_sdk/Logic/Output/__init__.py
spotON_sdk/Logic/Price/Price_Logic.py
spotON_sdk/Logic/Price/__init__.py
spotON_sdk/Logic/Price/bidding_zones.py
spotON_sdk/Logic/Price/countries.py
spotON_sdk/Logic/Price/customBaseModel.py
spotON_sdk/Logic/Price/markets.py
spotON_sdk/Logic/Price/spotON_Areas.py
spotON_sdk/Logic/Price/timeframes.py
spotON_sdk/data_helpers/BestHour.py
spotON_sdk/data_helpers/__init__.py
spotON_sdk/data_helpers/dataframe_modifier.py
spotON_sdk/data_helpers/mocks.py
spotON_sdk/data_helpers/time_helper.py
spotON_sdk/private_functions/Sensor_Device_function.py
spotON_sdk/private_functions/create_spotON_Areas.py
spotON_sdk/private_functions/create_token.py
spotON_sdk/private_functions/make_json.py
spotON_sdk/private_functions/pricelogic_functions.py
spotON_sdk/private_functions/userstate_function.py
spoton_sdk-0.0.6.13.dist-info/LICENSE
spoton_sdk-0.0.6.13.dist-info/WHEEL
spoton_sdk-0.0.6.13.dist-info/METADATA
spoton_sdk-0.0.6.13.dist-info/RECORD
